[{"pk": 1, "model": "profiles.datadomain", "fields": {"slug": "overview", "name": "Overview", "weight": 1, "subdomains": [13], "subdomain_only": false, "order": null}}, {"pk": 2, "model": "profiles.datadomain", "fields": {"slug": "demographics", "name": "Demographics", "weight": 3, "subdomains": [13, 53, 12, 14, 16, 15, 17, 18], "subdomain_only": false, "order": null}}, {"pk": 3, "model": "profiles.datadomain", "fields": {"slug": "economy", "name": "Economy", "weight": 5, "subdomains": [25, 26, 27, 28, 29], "subdomain_only": false, "order": null}}, {"pk": 4, "model": "profiles.datadomain", "fields": {"slug": "housing", "name": "Housing", "weight": 7, "subdomains": [34, 54, 14, 35, 36, 37], "subdomain_only": false, "order": null}}, {"pk": 5, "model": "profiles.datadomain", "fields": {"slug": "education", "name": "Education", "weight": 4, "subdomains": [19, 20, 21, 22, 23, 24], "subdomain_only": false, "order": null}}, {"pk": 6, "model": "profiles.datadomain", "fields": {"slug": "health", "name": "Health", "weight": 6, "subdomains": [30, 31, 32, 33], "subdomain_only": false, "order": null}}, {"pk": 7, "model": "profiles.datadomain", "fields": {"slug": "public-safety", "name": "Public Safety", "weight": 10, "subdomains": [39, 40, 41], "subdomain_only": false, "order": null}}, {"pk": 12, "model": "profiles.datadomain", "fields": {"slug": "age-and-sex", "name": "Age and Sex", "weight": 3, "subdomains": [], "subdomain_only": true, "order": null}}, {"pk": 13, "model": "profiles.datadomain", "fields": {"slug": "demographics-overview", "name": "Demographics Overview", "weight": 1, "subdomains": [], "subdomain_only": true, "order": null}}, {"pk": 14, "model": "profiles.datadomain", "fields": {"slug": "household-composition", "name": "Household Composition", "weight": 4, "subdomains": [], "subdomain_only": true, "order": null}}, {"pk": 15, "model": "profiles.datadomain", "fields": {"slug": "disabilities", "name": "Disabilities", "weight": 6, "subdomains": [], "subdomain_only": true, "order": null}}, {"pk": 16, "model": "profiles.datadomain", "fields": {"slug": "race-and-ethnicity", "name": "Race and Ethnicity", "weight": 5, "subdomains": [], "subdomain_only": true, "order": null}}, {"pk": 17, "model": "profiles.datadomain", "fields": {"slug": "language", "name": "Language", "weight": 7, "subdomains": [], "subdomain_only": true, "order": null}}, {"pk": 18, "model": "profiles.datadomain", "fields": {"slug": "birthplace", "name": "Birthplace", "weight": 8, "subdomains": [], "subdomain_only": true, "order": null}}, {"pk": 19, "model": "profiles.datadomain", "fields": {"slug": "education-overview", "name": "Education Overview", "weight": 1, "subdomains": [], "subdomain_only": true, "order": null}}, {"pk": 20, "model": "profiles.datadomain", "fields": {"slug": "school-enrollment", "name": "School Enrollment", "weight": 2, "subdomains": [], "subdomain_only": true, "order": null}}, {"pk": 21, "model": "profiles.datadomain", "fields": {"slug": "school-readiness", "name": "School Readiness", "weight": 3, "subdomains": [], "subdomain_only": true, "order": null}}, {"pk": 22, "model": "profiles.datadomain", "fields": {"slug": "student-performance", "name": "Student Performance", "weight": 4, "subdomains": [], "subdomain_only": true, "order": null}}, {"pk": 23, "model": "profiles.datadomain", "fields": {"slug": "educational-attainment", "name": "Educational Attainment", "weight": 5, "subdomains": [], "subdomain_only": true, "order": null}}, {"pk": 24, "model": "profiles.datadomain", "fields": {"slug": "access-education-services", "name": "Access to Education Services", "weight": 6, "subdomains": [], "subdomain_only": true, "order": null}}, {"pk": 25, "model": "profiles.datadomain", "fields": {"slug": "economy-overview", "name": "Economy Overview", "weight": 1, "subdomains": [], "subdomain_only": true, "order": null}}, {"pk": 26, "model": "profiles.datadomain", "fields": {"slug": "income", "name": "Income", "weight": 2, "subdomains": [], "subdomain_only": true, "order": null}}, {"pk": 27, "model": "profiles.datadomain", "fields": {"slug": "poverty", "name": "Poverty", "weight": 3, "subdomains": [], "subdomain_only": true, "order": null}}, {"pk": 28, "model": "profiles.datadomain", "fields": {"slug": "employment", "name": "Employment", "weight": 4, "subdomains": [], "subdomain_only": true, "order": null}}, {"pk": 29, "model": "profiles.datadomain", "fields": {"slug": "employment-opportunities-support", "name": "Employment Opportunities and Support", "weight": 5, "subdomains": [], "subdomain_only": true, "order": null}}, {"pk": 30, "model": "profiles.datadomain", "fields": {"slug": "health-overview", "name": "Health Overview", "weight": 1, "subdomains": [], "subdomain_only": true, "order": null}}, {"pk": 31, "model": "profiles.datadomain", "fields": {"slug": "maternal-and-child-health", "name": "Maternal and Child Health", "weight": 2, "subdomains": [], "subdomain_only": true, "order": null}}, {"pk": 32, "model": "profiles.datadomain", "fields": {"slug": "lead-and-asthma", "name": "Lead and Asthma", "weight": 3, "subdomains": [], "subdomain_only": true, "order": null}}, {"pk": 33, "model": "profiles.datadomain", "fields": {"slug": "access-health-services", "name": "Access to Health Services", "weight": 4, "subdomains": [], "subdomain_only": true, "order": null}}, {"pk": 34, "model": "profiles.datadomain", "fields": {"slug": "housing-oviewview", "name": "Housing Overview", "weight": 1, "subdomains": [], "subdomain_only": true, "order": null}}, {"pk": 35, "model": "profiles.datadomain", "fields": {"slug": "housing-occupancy", "name": "Occupancy", "weight": 5, "subdomains": [], "subdomain_only": true, "order": null}}, {"pk": 36, "model": "profiles.datadomain", "fields": {"slug": "physical-characteristics", "name": "Physical Characteristics", "weight": 6, "subdomains": [], "subdomain_only": true, "order": null}}, {"pk": 37, "model": "profiles.datadomain", "fields": {"slug": "housing-affordability", "name": "Affordability", "weight": 7, "subdomains": [], "subdomain_only": true, "order": null}}, {"pk": 39, "model": "profiles.datadomain", "fields": {"slug": "public-safety-overview", "name": "Public Safety Overview", "weight": 1, "subdomains": [], "subdomain_only": true, "order": null}}, {"pk": 40, "model": "profiles.datadomain", "fields": {"slug": "crimes-and-arrests", "name": "Crimes and Arrests", "weight": 2, "subdomains": [], "subdomain_only": true, "order": null}}, {"pk": 41, "model": "profiles.datadomain", "fields": {"slug": "other-threats-safety", "name": "Other Threats to Safety", "weight": 3, "subdomains": [], "subdomain_only": true, "order": null}}, {"pk": 42, "model": "profiles.datadomain", "fields": {"slug": "environment", "name": "Environment", "weight": 8, "subdomains": [44, 45, 46], "subdomain_only": false, "order": null}}, {"pk": 43, "model": "profiles.datadomain", "fields": {"slug": "transportation", "name": "Transportation", "weight": 9, "subdomains": [47, 48, 49, 50, 51], "subdomain_only": false, "order": null}}, {"pk": 44, "model": "profiles.datadomain", "fields": {"slug": "environment-overview", "name": "Environment Overview", "weight": 1, "subdomains": [], "subdomain_only": true, "order": null}}, {"pk": 45, "model": "profiles.datadomain", "fields": {"slug": "parks-open-space-and-tree-cover", "name": "Parks, Open Space, and Tree Cover", "weight": 2, "subdomains": [], "subdomain_only": true, "order": null}}, {"pk": 46, "model": "profiles.datadomain", "fields": {"slug": "pollution-levels", "name": "Pollution Levels", "weight": 3, "subdomains": [], "subdomain_only": true, "order": null}}, {"pk": 47, "model": "profiles.datadomain", "fields": {"slug": "transportation-overview", "name": "Transportation Overview", "weight": 1, "subdomains": [], "subdomain_only": true, "order": null}}, {"pk": 48, "model": "profiles.datadomain", "fields": {"slug": "public-transit-access", "name": "Public Transit Access", "weight": 2, "subdomains": [], "subdomain_only": true, "order": null}}, {"pk": 49, "model": "profiles.datadomain", "fields": {"slug": "vehicle-access", "name": "Vehicle Access", "weight": 3, "subdomains": [], "subdomain_only": true, "order": null}}, {"pk": 50, "model": "profiles.datadomain", "fields": {"slug": "mode-transportation", "name": "Mode of Transportation", "weight": 4, "subdomains": [], "subdomain_only": true, "order": null}}, {"pk": 51, "model": "profiles.datadomain", "fields": {"slug": "distance-work", "name": "Distance to Work", "weight": 5, "subdomains": [], "subdomain_only": true, "order": null}}, {"pk": 53, "model": "profiles.datadomain", "fields": {"slug": "population", "name": "Population", "weight": 2, "subdomains": [], "subdomain_only": true, "order": null}}, {"pk": 54, "model": "profiles.datadomain", "fields": {"slug": "tenure", "name": "Tenure (Rent/Own)", "weight": 2, "subdomains": [], "subdomain_only": true, "order": null}}]